{
  "source": "dailyfaceoff.com",
  "updated_at": "2026-04-26 19:51:00 UTC",
  "matchups": [
    {
      "away": {
        "team": "buffalo-sabres",
        "goalie": "ALEX LYON",
        "status": "Confirmed",
        "headshotUrl": "https://api.dailyfaceoff.com/uploads/player/headshot/2873/Lyon-Alex_BUF-1_.png",
        "stats": {
          "record": "20-10-4",
          "gaa": "2.77",
          "svpct": "0.906",
          "so": 3
        }
      },
      "home": {
        "team": "boston-bruins",
        "goalie": "JEREMY SWAYMAN",
        "status": "Confirmed",
        "headshotUrl": "https://api.dailyfaceoff.com/uploads/player/headshot/28098/Swayman-Jeremy_BOS-2024_1.png",
        "stats": {
          "record": "31-18-4",
          "gaa": "2.71",
          "svpct": "0.907",
          "so": 2
        }
      },
      "date": "2026-04-26",
      "time": "14:00"
    },
    {
      "away": {
        "team": "colorado-avalanche",
        "goalie": "SCOTT WEDGEWOOD",
        "status": "Unconfirmed",
        "headshotUrl": "https://api.dailyfaceoff.com/uploads/player/headshot/1873/Wedgewood-Scott_COL-2025_.png",
        "stats": {
          "record": "31-6-6",
          "gaa": "2.02",
          "svpct": "0.921",
          "so": 4
        }
      },
      "home": {
        "team": "los-angeles-kings",
        "goalie": "ANTON FORSBERG",
        "status": "Unconfirmed",
        "headshotUrl": "https://api.dailyfaceoff.com/uploads/player/headshot/2394/Forsberg-Anton_LAK-12-17-25_.png",
        "stats": {
          "record": "16-12-5",
          "gaa": "2.57",
          "svpct": "0.908",
          "so": 3
        }
      },
      "date": "2026-04-26",
      "time": "16:30"
    },
    {
      "away": {
        "team": "tampa-bay-lightning",
        "goalie": "ANDREI VASILEVSKIY",
        "status": "Unconfirmed",
        "headshotUrl": "https://api.dailyfaceoff.com/uploads/player/headshot/2413/Vasilevskiy-Andrei_TBL-2024_.png",
        "stats": {
          "record": "38-15-4",
          "gaa": "2.35",
          "svpct": "0.909",
          "so": 1
        }
      },
      "home": {
        "team": "montreal-canadiens",
        "goalie": "JAKUB DOBES",
        "status": "Unconfirmed",
        "headshotUrl": "https://api.dailyfaceoff.com/uploads/player/headshot/31895/Dobes-Jakub_MTL-2024_.png",
        "stats": {
          "record": "29-10-4",
          "gaa": "2.78",
          "svpct": "0.901",
          "so": 0
        }
      },
      "date": "2026-04-26",
      "time": "19:00"
    },
    {
      "away": {
        "team": "edmonton-oilers",
        "goalie": "CONNOR INGRAM",
        "status": "Unconfirmed",
        "headshotUrl": "https://api.dailyfaceoff.com/uploads/player/headshot/4523/Ingram-Connor_EDM-2026_.png",
        "stats": {
          "record": "16-10-3",
          "gaa": "2.6",
          "svpct": "0.898",
          "so": 2
        }
      },
      "home": {
        "team": "anaheim-ducks",
        "goalie": "LUKAS DOSTAL",
        "status": "Unconfirmed",
        "headshotUrl": "https://api.dailyfaceoff.com/uploads/player/headshot/29143/Dostal-Lukas_ANA-2026_.png",
        "stats": {
          "record": "30-20-4",
          "gaa": "3.12",
          "svpct": "0.888",
          "so": 0
        }
      },
      "date": "2026-04-26",
      "time": "21:30"
    }
  ]
}